openinference/instrumentation/.gitignore
openinference/instrumentation/__init__.py
openinference/instrumentation/_attributes.py
openinference/instrumentation/_capture.py
openinference/instrumentation/_projects.py
openinference/instrumentation/_spans.py
openinference/instrumentation/_spans.pyi
openinference/instrumentation/_tracer_providers.py
openinference/instrumentation/_tracers.py
openinference/instrumentation/_types.py
openinference/instrumentation/config.py
openinference/instrumentation/context_attributes.py
openinference/instrumentation/helpers.py
openinference/instrumentation/logging.py
openinference/instrumentation/py.typed
openinference/instrumentation/version.py
openinference_instrumentation-0.1.44.dist-info/METADATA
openinference_instrumentation-0.1.44.dist-info/WHEEL
openinference_instrumentation-0.1.44.dist-info/licenses/LICENSE
openinference_instrumentation-0.1.44.dist-info/RECORD
