Metadata-Version: 2.4
Name: openinference-instrumentation
Version: 0.1.44
Summary: OpenInference instrumentation utilities
Project-URL: Homepage, https://github.com/Arize-ai/openinference/tree/main/python/openinference-instrumentation
Author-email: OpenInference Authors <oss@arize.com>
License-Expression: Apache-2.0
License-File: LICENSE
Classifier: Development Status :: 5 - Production/Stable
Classifier: Intended Audience :: Developers
Classifier: License :: OSI Approved :: Apache Software License
Classifier: Programming Language :: Python
Classifier: Programming Language :: Python :: 3
Classifier: Programming Language :: Python :: 3.9
Classifier: Programming Language :: Python :: 3.10
Classifier: Programming Language :: Python :: 3.11
Classifier: Programming Language :: Python :: 3.12
Classifier: Programming Language :: Python :: 3.13
Classifier: Programming Language :: Python :: 3.14
Requires-Python: <3.15,>=3.9
Requires-Dist: openinference-semantic-conventions>=0.1.26
Requires-Dist: opentelemetry-api
Requires-Dist: opentelemetry-sdk
Requires-Dist: wrapt<2,>=1.14.0
Provides-Extra: test
Requires-Dist: jsonschema; extra == 'test'
Requires-Dist: openai; extra == 'test'
Requires-Dist: pydantic>=2.0.0; extra == 'test'
Requires-Dist: pytest-asyncio; extra == 'test'
Requires-Dist: pytest-recording; extra == 'test'
Requires-Dist: types-jsonschema; extra == 'test'
